LICENSE.txt
MANIFEST.in
README.rst
setup.py
mpltex/__init__.py
mpltex/_version.py
mpltex/acs.py
mpltex/aps.py
mpltex/colors.py
mpltex/general.py
mpltex/layout.py
mpltex/presentation.py
mpltex/rsc.py
mpltex/styles.py
mpltex/web.py
mpltex.egg-info/PKG-INFO
mpltex.egg-info/SOURCES.txt
mpltex.egg-info/dependency_links.txt
mpltex.egg-info/not-zip-safe
mpltex.egg-info/requires.txt
mpltex.egg-info/top_level.txt