Metadata-Version: 1.1
Name: mpltex
Version: 0.5.1
Summary: mpltex is a python package for creating publication-quality plots using matplotlib.
Home-page: https://github.com/liuyxpp/mpltex
Author: Yi-Xin Liu
Author-email: liuyxpp@gmail.com
License: BSD
Platform: UNKNOWN
Classifier: Development Status :: 4 - Beta
Classifier: Intended Audience :: Science/Research
Classifier: Intended Audience :: Developers
Classifier: Intended Audience :: Education
Classifier: License :: OSI Approved :: BSD License
Classifier: Operating System :: OS Independent
Classifier: Programming Language :: Python
Classifier: Topic :: Scientific/Engineering
Classifier: Topic :: Education
